{
    "os": "Windows-10-10.0.19042-SP0",
    "python": "3.9.7",
    "heartbeatAt": "2021-11-07T03:53:03.431001",
    "startedAt": "2021-11-07T03:52:59.265208",
    "docker": null,
    "gpu": "NVIDIA GeForce RTX 3060 Laptop GPU",
    "gpu_count": 1,
    "cpu_count": 12,
    "cuda": null,
    "args": [
        "--img",
        "64",
        "--batch",
        "8",
        "--epochs",
        "10",
        "--data",
        "coco128.yaml",
        "--weights",
        "yolov5s.pt",
        "--cache"
    ],
    "state": "running",
    "program": "C:\\Users\\User\\Desktop\\yolov5-new-20211105T100344Z-001 - Copy\\yolov5-new\\train.py",
    "codePath": "yolov5-new\\train.py",
    "host": "LAPTOP-EQET11T7",
    "username": "User",
    "executable": "C:\\Python39\\python.exe"
}
